wsn_sim/__init__.py
wsn_sim/cli.py
wsn_sim/network.py
wsn_sim/node.py
wsn_sim-0.0.0.dist-info/LICENSE.txt
wsn_sim-0.0.0.dist-info/METADATA
wsn_sim-0.0.0.dist-info/WHEEL
wsn_sim-0.0.0.dist-info/entry_points.txt
wsn_sim-0.0.0.dist-info/top_level.txt
wsn_sim-0.0.0.dist-info/RECORD
