Metadata-Version: 2.1
Name: wsn_sim
Version: 0.0.0
Summary: Wireless Sensor Network Simulator with AODV and DSR protocols
Home-page: https://github.com/deepak7376/wsn_sim
Author: Deepak Yadav
Author-email: dky.united@gmail.com
License-File: LICENSE.txt
Requires-Dist: click
Requires-Dist: networkx
Requires-Dist: matplotlib
Requires-Dist: numpy
Requires-Dist: configparser
